obs_dev/__init__.py
obs_dev/consts.py
obs_dev/cmds/plugin.py
obs_dev/cmds/vault.py
obs_dev/data/manifest_json.py
obs_dev/data/package_json.py
obs_dev/data/plugin-template.zip
obs_dev/data/sample_code.ts
obs_dev/data/vault.zip
obs_dev/utils/__init__.py
obs_dev/utils/plugin.py
obs_dev-0.1.0.dist-info/METADATA
obs_dev-0.1.0.dist-info/WHEEL
obs_dev-0.1.0.dist-info/entry_points.txt
obs_dev-0.1.0.dist-info/licenses/LICENSE
obs_dev-0.1.0.dist-info/RECORD
