Metadata-Version: 2.4
Name: obs-dev
Version: 0.1.0
Summary: Add your description here
Author-email: ZackaryW <36378555+ZackaryW@users.noreply.github.com>
License-File: LICENSE
Requires-Python: >=3.8
Requires-Dist: click>=8.1.8
Requires-Dist: packaging>=25.0
Provides-Extra: watch
Requires-Dist: watchdog>=3.0.0; extra == 'watch'
